whale_client/__init__.py
whale_client/api/__init__.py
whale_client/api/entry.py
whale_client/models/__init__.py
whale_client/models/api/entry.py
whale_client/models/application.py
whale_client/models/manager.py
whale_client/models/table.py
whale_client/sandbox/__init__.py
whale_client/sandbox/main.py
whale_client-0.1.3.dist-info/METADATA
whale_client-0.1.3.dist-info/WHEEL
whale_client-0.1.3.dist-info/RECORD
